{
  "id": "cft:noble",
  "maxHappiness": 24000.0,
  "matingHappinessThreshold": 2400.0,
  "spontaneouslySpawnPopulation": 0,
  "needs": [
    "cft:cake_need",
    "cft:diamond_need",
    "cft:beef_need",
    "cft:noble_home"
  ],
  "upgrades": [],
  "downgrades": [
    {
      "nextClass": "cft:patrician",
      "requiredHappiness": 600,
      "requiredNeeds": [
        {
          "need": "cft:diamond_need",
          "satisfactionThreshold": 0.50
        }
      ],
      "socialStructureRequirements": []
    },
    {
      "nextClass": "cft:artisan",
      "requiredHappiness": 400,
      "requiredNeeds": [
        {
          "need": "cft:cake_need",
          "satisfactionThreshold": 0.40
        }
      ],
      "socialStructureRequirements": []
    }
  ]
}
